loglite/__init__.py
loglite/log/__init__.py
loglite/log/logclient.py
loglite/log/version.py
aliyun_lite_log_python_sdk-0.1.3.dist-info/METADATA
aliyun_lite_log_python_sdk-0.1.3.dist-info/WHEEL
aliyun_lite_log_python_sdk-0.1.3.dist-info/top_level.txt
aliyun_lite_log_python_sdk-0.1.3.dist-info/RECORD
