Metadata-Version: 2.1
Name: aliyun-lite-log-python-sdk
Version: 0.1.3
Summary: Aliyun log Kafka ElasticSearch Plugin Python client SDK
Home-page: https://github.com/aliyun/aliyun-lite-log-python-sdk
Author: Aliyun
Author-email: UNKNOWN
License: UNKNOWN
Platform: UNKNOWN
Classifier: Development Status :: 5 - Production/Stable
Classifier: License :: OSI Approved :: MIT License
Classifier: Operating System :: OS Independent
Classifier: Programming Language :: Python :: 2.6
Classifier: Programming Language :: Python :: 2.7
Classifier: Programming Language :: Python :: Implementation :: PyPy
Requires-Dist: aliyun-log-python-sdk (>=0.6.44)
Requires-Dist: elasticsearch (<7.0.0,>=6.0.0)
Requires-Dist: kafka-python (>=1.4.4)
Requires-Dist: responses
